pypi_test_test/__init__.py
pypi_test_test-0.1.5.dist-info/WHEEL
pypi_test_test-0.1.5.dist-info/METADATA
pypi_test_test-0.1.5.dist-info/RECORD
