Metadata-Version: 2.1
Name: pypi-test-test
Version: 0.1.5
Summary: This is an amazing description
Author: amitkummer
Author-email: amit.kummer@gmail.com
Requires-Python: >=3.8,<4.0
Classifier: Programming Language :: Python :: 3
Classifier: Programming Language :: Python :: 3.8
Classifier: Programming Language :: Python :: 3.9
